{"LongJump": 50, "BlowingCandles": 13, "Haircut": 33, "Basketball": 7, "UnevenBars": 95, "SkateBoarding": 79, "TennisSwing": 91, "Lunges": 51, "MoppingFloor": 54, "BabyCrawling": 3, "BreastStroke": 18, "HeadMassage": 38, "HammerThrow": 34, "PlayingSitar": 64, "Bowling": 15, "Shotput": 78, "ThrowDiscus": 92, "ApplyLipstick": 1, "RockClimbingIndoor": 73, "TableTennisShot": 89, "PizzaTossing": 57, "PlayingDaf": 59, "ParallelBars": 56, "Skijet": 81, "JumpRope": 46, "BaseballPitch": 6, "Archery": 2, "HighJump": 39, "Rowing": 75, "HandstandWalking": 37, "PommelHorse": 68, "WalkingWithDog": 97, "HorseRiding": 41, "SkyDiving": 82, "CuttingInKitchen": 24, "Mixing": 53, "BandMarching": 5, "Biking": 10, "Fencing": 27, "ApplyEyeMakeup": 0, "WritingOnBoard": 99, "Nunchucks": 55, "PlayingDhol": 60, "Surfing": 87, "JugglingBalls": 45, "JumpingJack": 47, "CleanAndJerk": 20, "BoxingSpeedBag": 17, "FieldHockeyPenalty": 28, "ShavingBeard": 77, "PlayingCello": 58, "HulaHoop": 42, "WallPushups": 98, "GolfSwing": 32, "Kayaking": 48, "Skiing": 80, "Punch": 70, "BasketballDunk": 8, "CliffDiving": 21, "SoccerPenalty": 84, "PullUps": 69, "FloorGymnastics": 29, "IceDancing": 43, "YoYo": 100, "BrushingTeeth": 19, "HandstandPushups": 36, "TrampolineJumping": 93, "SalsaSpin": 76, "Hammering": 35, "Billiards": 11, "PushUps": 71, "FrontCrawl": 31, "FrisbeeCatch": 30, "SumoWrestling": 86, "PoleVault": 67, "BenchPress": 9, "BlowDryHair": 12, "RopeClimbing": 74, "Diving": 25, "PlayingPiano": 63, "Drumming": 26, "JavelinThrow": 44, "PlayingTabla": 65, "HorseRace": 40, "TaiChi": 90, "CricketBowling": 22, "Rafting": 72, "CricketShot": 23, "StillRings": 85, "SoccerJuggling": 83, "PlayingViolin": 66, "PlayingFlute": 61, "BodyWeightSquats": 14, "VolleyballSpiking": 96, "BoxingPunchingBag": 16, "Knitting": 49, "MilitaryParade": 52, "Typing": 94, "BalanceBeam": 4, "Swing": 88, "PlayingGuitar": 62}